ayon/__init__.py
ayon-0.1.0.dist-info/METADATA
ayon-0.1.0.dist-info/WHEEL
ayon-0.1.0.dist-info/top_level.txt
ayon-0.1.0.dist-info/RECORD
